LICENSE
MANIFEST.in
Pipfile
Pipfile.lock
README.md
setup.py
moocal/__init__.py
moocal/__main__.py
moocal/__version__.py
moocal.egg-info/PKG-INFO
moocal.egg-info/SOURCES.txt
moocal.egg-info/dependency_links.txt
moocal.egg-info/entry_points.txt
moocal.egg-info/requires.txt
moocal.egg-info/top_level.txt
moocal/mooc/__init__.py
moocal/mooc/cnmooc.py
moocal/mooc/icourse163.py
moocal/mooc/icourses.py
moocal/mooc/icourses_share.py
moocal/mooc/livedu.py
moocal/mooc/open_163.py
moocal/mooc/study_163.py
moocal/mooc/study_mooc.py
moocal/mooc/utils.py
moocal/mooc/xuetangx.py